mathutils/__init__.py
mathutils/mathutils.py
ali025-0.1.0.dist-info/METADATA
ali025-0.1.0.dist-info/WHEEL
ali025-0.1.0.dist-info/top_level.txt
ali025-0.1.0.dist-info/RECORD
