Metadata-Version: 2.4
Name: Ali025
Version: 0.1.0
Summary: My first python library
Author: ali tarrab
